rbwr/__init__.py
rbwr/either.py
rbwr/option.py
rbwr/py.typed
rbwr/result.py
rbwr-0.2.0.dist-info/METADATA
rbwr-0.2.0.dist-info/WHEEL
rbwr-0.2.0.dist-info/RECORD
