Metadata-Version: 2.4
Name: rbwr
Version: 0.2.0
Summary: Rather be writing Rust.
Project-URL: documentation, https://charles.gitlab-pages.computer.surgery/rbwr
Project-URL: source, https://gitlab.computer.surgery/charles/rbwr
License-Expression: MIT OR Apache-2.0
Keywords: enum,rust,sum,tagged,types,union
Classifier: Intended Audience :: Developers
Classifier: Operating System :: OS Independent
Classifier: Topic :: Software Development :: Libraries
Classifier: Typing :: Typed
Requires-Python: >=3.13
